{"version":"0.4","title":"Weddingpress 014","type":"page","content":[{"id":"23f07d24","settings":{"background_background":"classic","shape_divider_bottom_negative":"yes","padding":{"unit":"px","top":"0","right":"0","bottom":"0","left":"0","isLinked":false},"background_color":"#FFF1CF"},"elements":[{"id":"55b6d183","settings":{"_column_size":100,"background_background":"classic","background_color":"rgba(255,211,105,0.75)","background_overlay_background":"classic","background_overlay_image":{"id":"397","url":"https:\/\/tombol.space\/wp-content\/uploads\/2020\/12\/pexels-photo-256737.png"},"background_overlay_image_tablet":{"id":"397","url":"https:\/\/tombol.space\/wp-content\/uploads\/2020\/12\/pexels-photo-256737.png"},"background_overlay_image_mobile":{"id":"397","url":"https:\/\/tombol.space\/wp-content\/uploads\/2020\/12\/pexels-photo-256737.png"},"background_overlay_position":"initial","background_overlay_position_tablet":"initial","background_overlay_position_mobile":"center center","background_overlay_xpos_mobile":{"unit":"px","size":-216,"sizes":[]},"background_overlay_ypos":{"unit":"px","size":-304,"sizes":[]},"background_overlay_attachment":"fixed","background_overlay_repeat":"no-repeat","background_overlay_repeat_tablet":"no-repeat","background_overlay_size":"initial","background_overlay_size_tablet":"cover","background_overlay_bg_width":{"unit":"%","size":97,"sizes":[]},"background_overlay_opacity":{"unit":"px","size":0.33,"sizes":[]},"border_radius":{"unit":"px","top":"0","right":"0","bottom":"0","left":"0","isLinked":false},"margin_tablet":{"unit":"px","top":"0","right":"20","bottom":"0","left":"20","isLinked":false},"margin_mobile":{"unit":"px","top":"0","right":"10","bottom":"0","left":"10","isLinked":false},"padding":{"unit":"px","top":"100","right":"0","bottom":"100","left":"0","isLinked":false}},"elements":[{"id":"331f8fab","settings":{"title":"THE WEDDING OF\n","header_size":"p","align":"center","title_color":"#263f44","typography_typography":"custom","typography_font_family":"Times New Roman","typography_font_size":{"unit":"px","size":22,"sizes":[]},"typography_letter_spacing":{"unit":"px","size":2,"sizes":[]}},"elements":[],"isInner":false,"widgetType":"heading","elType":"widget"},{"id":"2f5cdd9","settings":{"title":"ANDY & ZHEA","header_size":"h1","align":"center","title_color":"#263f44","typography_typography":"custom","typography_font_family":"Croissant One","typography_font_size":{"unit":"px","size":60,"sizes":[]},"typography_font_weight":"500","text_shadow_text_shadow_type":"yes","text_shadow_text_shadow":{"horizontal":0,"vertical":4,"blur":4,"color":"rgba(0,0,0,0.19)"}},"elements":[],"isInner":false,"widgetType":"heading","elType":"widget"},{"id":"b3e7e23","settings":{"title":"12 DESEMBER 20XX","header_size":"p","align":"center","title_color":"#263f44","typography_typography":"custom","typography_font_family":"Times New Roman","typography_font_size":{"unit":"px","size":22,"sizes":[]},"typography_letter_spacing":{"unit":"px","size":2,"sizes":[]}},"elements":[],"isInner":false,"widgetType":"heading","elType":"widget"},{"id":"59469ade","settings":{"text":"SAVE THE DATE","link":{"url":"#date","is_external":"","nofollow":"","custom_attributes":""},"align":"center","size":"md","fb_value":"0","typography_typography":"custom","typography_font_family":"Rubik","typography_font_size":{"unit":"px","size":20,"sizes":[]},"typography_font_weight":"400","background_color":"#61CE7000","button_background_hover_color":"#FFD774","button_hover_border_color":"#263F44","border_border":"solid","border_width":{"unit":"px","top":"2","right":"2","bottom":"2","left":"2","isLinked":true},"border_radius":{"unit":"px","top":"7","right":"7","bottom":"7","left":"7","isLinked":true},"_margin":{"unit":"px","top":"20","right":"0","bottom":"20","left":"0","isLinked":false},"button_text_color":"#263F44","hover_color":"#263F44"},"elements":[],"isInner":false,"widgetType":"button","elType":"widget"}],"isInner":false,"elType":"column"}],"isInner":false,"elType":"section"},{"id":"3c846bd5","settings":{"background_background":"classic","background_color":"#FFF1CF"},"elements":[{"id":"2fb2b597","settings":{"_column_size":100,"background_background":"classic","background_color":"#ffd369","margin_tablet":{"unit":"px","top":"0","right":"20","bottom":"0","left":"20","isLinked":false},"margin_mobile":{"unit":"px","top":"0","right":"10","bottom":"0","left":"10","isLinked":false},"padding":{"unit":"px","top":"75","right":"0","bottom":"75","left":"0","isLinked":false}},"elements":[{"id":"3d9673b4","settings":{"image":{"id":"541","url":"https:\/\/tombol.space\/wp-content\/uploads\/2020\/12\/Asset-1.png"},"image_size":"full","align":"center","width":{"unit":"%","size":15,"sizes":[]},"width_tablet":{"unit":"%","size":25,"sizes":[]},"space":{"unit":"%","size":100,"sizes":[]},"space_tablet":{"unit":"%","size":100,"sizes":[]},"_margin":{"unit":"px","top":"-120","right":"0","bottom":"0","left":"0","isLinked":false},"_margin_tablet":{"unit":"px","top":"-115","right":"0","bottom":"0","left":"0","isLinked":false},"fb_value":"0"},"elements":[],"isInner":false,"widgetType":"image","elType":"widget"},{"id":"a6bb649","settings":{"title":"Appreciate For Your Coming\n\n","align":"center","title_color":"#015668","typography_typography":"custom","typography_font_family":"Source Serif Pro","_padding_mobile":{"unit":"px","top":"0","right":"20","bottom":"0","left":"20","isLinked":false},"header_size":"p","typography_font_size":{"unit":"px","size":22,"sizes":[]}},"elements":[],"isInner":false,"widgetType":"heading","elType":"widget"},{"id":"2e27138d","settings":{"structure":"20"},"elements":[{"id":"70d2d6a2","settings":{"_column_size":50,"_inline_size":null,"animation":"fadeInUp"},"elements":[{"id":"5733bc66","settings":{"image":{"id":"528","url":"https:\/\/tombol.space\/wp-content\/uploads\/2020\/12\/02-7.png"},"title_text":"Andy Hermawan","description_text":"<b>Son of<br><\/b>Mr. Father Name & Mrs. Mother Name","image_space":{"unit":"px","size":0,"sizes":[]},"image_space_mobile":{"unit":"px","size":7,"sizes":[]},"image_size_mobile":{"unit":"%","size":75,"sizes":[]},"content_vertical_alignment":"middle","title_bottom_space":{"unit":"px","size":0,"sizes":[]},"title_color":"#015668","title_typography_typography":"custom","title_typography_font_family":"Source Serif Pro","title_typography_font_size":{"unit":"px","size":25,"sizes":[]},"description_color":"#263f44","description_typography_typography":"custom","description_typography_font_family":"Roboto Condensed","description_typography_font_weight":"400","text_align":"center","title_size":"p"},"elements":[],"isInner":false,"widgetType":"image-box","elType":"widget"},{"id":"3ad74030","settings":{"social_icon_list":[{"social_icon":{"value":"fab fa-facebook","library":"fa-brands"},"_id":"8e8a762"},{"social_icon":{"value":"fab fa-twitter","library":"fa-brands"},"_id":"92e7cbe"},{"social_icon":{"value":"fab fa-whatsapp","library":"fa-brands"},"_id":"305f5e1"},{"social_icon":{"value":"fab fa-instagram","library":"fa-brands"},"_id":"00c4ce7"}],"shape":"circle","icon_color":"custom","icon_primary_color":"rgba(1,86,104,0.99)","icon_secondary_color":"#ffffff","icon_spacing":{"unit":"px","size":14,"sizes":[]},"hover_primary_color":"#ffffff","hover_secondary_color":"#015668"},"elements":[],"isInner":false,"widgetType":"social-icons","elType":"widget"}],"isInner":true,"elType":"column"},{"id":"2cd03a72","settings":{"_column_size":50,"_inline_size":null,"animation":"fadeInUp","animation_delay":300},"elements":[{"id":"3617bba6","settings":{"image":{"id":"529","url":"https:\/\/tombol.space\/wp-content\/uploads\/2020\/12\/03-5.png"},"title_text":"Fauziah Ratnasari","description_text":"<b>Daughter of<br><\/b>Mr. Father Name &amp; Mrs. Mother Name","image_space":{"unit":"px","size":0,"sizes":[]},"image_space_mobile":{"unit":"px","size":7,"sizes":[]},"image_size_mobile":{"unit":"%","size":75,"sizes":[]},"content_vertical_alignment":"middle","title_bottom_space":{"unit":"px","size":0,"sizes":[]},"title_color":"#015668","title_typography_typography":"custom","title_typography_font_family":"Source Serif Pro","title_typography_font_size":{"unit":"px","size":25,"sizes":[]},"description_color":"#263f44","description_typography_typography":"custom","description_typography_font_family":"Roboto Condensed","description_typography_font_weight":"400","text_align":"center","title_size":"p"},"elements":[],"isInner":false,"widgetType":"image-box","elType":"widget"},{"id":"7491470d","settings":{"social_icon_list":[{"social_icon":{"value":"fab fa-facebook","library":"fa-brands"},"_id":"8e8a762"},{"social_icon":{"value":"fab fa-twitter","library":"fa-brands"},"_id":"92e7cbe"},{"social_icon":{"value":"fab fa-whatsapp","library":"fa-brands"},"_id":"305f5e1"},{"social_icon":{"value":"fab fa-instagram","library":"fa-brands"},"_id":"00c4ce7"}],"shape":"circle","icon_color":"custom","icon_primary_color":"rgba(1,86,104,0.99)","icon_secondary_color":"#ffffff","icon_spacing":{"unit":"px","size":14,"sizes":[]},"hover_primary_color":"#ffffff","hover_secondary_color":"#015668"},"elements":[],"isInner":false,"widgetType":"social-icons","elType":"widget"}],"isInner":true,"elType":"column"}],"isInner":true,"elType":"section"}],"isInner":false,"elType":"column"}],"isInner":false,"elType":"section"},{"id":"5c618d9b","settings":{"padding_mobile":{"unit":"px","top":"0","right":"0","bottom":"0","left":"0","isLinked":false},"background_background":"classic","background_color":"#FFF1CF"},"elements":[{"id":"6fb70f80","settings":{"_column_size":100,"background_background":"classic","background_color":"#015668","background_overlay_background":"classic","background_overlay_image":{"id":"531","url":"https:\/\/tombol.space\/wp-content\/uploads\/2020\/12\/1.jpg"},"background_overlay_repeat":"repeat","background_overlay_size":"cover","background_overlay_opacity":{"unit":"px","size":0.09,"sizes":[]},"padding":{"unit":"px","top":"100","right":"0","bottom":"100","left":"0","isLinked":false},"margin_tablet":{"unit":"px","top":"0","right":"20","bottom":"0","left":"20","isLinked":false},"margin_mobile":{"unit":"px","top":"0","right":"10","bottom":"0","left":"10","isLinked":false},"padding_mobile":{"unit":"px","top":"50","right":"20","bottom":"50","left":"20","isLinked":false}},"elements":[{"id":"1a3c5181","settings":{"anchor":"date"},"elements":[],"isInner":false,"widgetType":"menu-anchor","elType":"widget"},{"id":"18720e95","settings":{"title":"With Great Pleasure","align":"center","title_color":"#ffffff","typography_typography":"custom","typography_font_family":"Source Serif Pro","typography_letter_spacing":{"unit":"px","size":0,"sizes":[]},"header_size":"p","typography_font_size":{"unit":"px","size":22,"sizes":[]}},"elements":[],"isInner":false,"widgetType":"heading","elType":"widget"},{"id":"76259118","settings":{"title":"Invite You\n","header_size":"p","align":"center","title_color":"#ffffff","typography_typography":"custom","typography_font_family":"Croissant One","typography_font_size":{"unit":"px","size":60,"sizes":[]},"typography_font_weight":"500","text_shadow_text_shadow_type":"yes","text_shadow_text_shadow":{"horizontal":0,"vertical":6,"blur":6,"color":"rgba(0,0,0,0.19)"},"_margin":{"unit":"px","top":"-22","right":"0","bottom":"0","left":"0","isLinked":false}},"elements":[],"isInner":false,"widgetType":"heading","elType":"widget"},{"id":"5b6588b5","settings":{"title":"To Celebrate Our marriage\n","align":"center","title_color":"#ffffff","typography_typography":"custom","typography_font_family":"Source Serif Pro","typography_letter_spacing":{"unit":"px","size":1.1,"sizes":[]},"_margin":{"unit":"px","top":"-17","right":"0","bottom":"0","left":"0","isLinked":false},"header_size":"p","typography_font_size":{"unit":"px","size":22,"sizes":[]}},"elements":[],"isInner":false,"widgetType":"heading","elType":"widget"},{"id":"4120b343","settings":{"title":"12 Desember 20xx","header_size":"p","align":"center","title_color":"#ffd369","typography_typography":"custom","typography_font_family":"Croissant One","typography_font_size":{"unit":"px","size":50,"sizes":[]},"typography_font_weight":"500","text_shadow_text_shadow_type":"yes","text_shadow_text_shadow":{"horizontal":0,"vertical":6,"blur":6,"color":"rgba(0,0,0,0.19)"},"typography_letter_spacing":{"unit":"px","size":-3.1,"sizes":[]},"_margin":{"unit":"px","top":"0","right":"0","bottom":"0","left":"0","isLinked":false}},"elements":[],"isInner":false,"widgetType":"heading","elType":"widget"},{"id":"2c4935e2","settings":{"title":"<b>Rumah Kediaman<\/b>:<br>lorem ipsum dolor sit amet, consectetur adipiscing elit","header_size":"p","align":"center","title_color":"#ffffff","typography_typography":"custom","typography_font_family":"Crete Round","typography_font_size":{"unit":"px","size":20,"sizes":[]},"typography_font_weight":"400","typography_line_height":{"unit":"em","size":1.3,"sizes":[]}},"elements":[],"isInner":false,"widgetType":"heading","elType":"widget"},{"id":"41af820d","settings":{"structure":"20"},"elements":[{"id":"6db591d2","settings":{"_column_size":50,"_inline_size":null,"_inline_size_mobile":50},"elements":[{"id":"36809ebb","settings":{"selected_icon":{"value":"far fa-calendar-alt","library":"fa-regular"},"title_text":"","description_text":"Sunday,<br>12 Desember 201x","primary_color":"#ffd369","icon_space":{"unit":"px","size":20,"sizes":[]},"title_bottom_space":{"unit":"px","size":0,"sizes":[]},"title_color":"#c6c664","title_typography_typography":"custom","title_typography_font_family":"Parisienne","title_typography_font_size":{"unit":"px","size":33,"sizes":[]},"description_color":"#ffffff","description_typography_typography":"custom","description_typography_font_family":"Playfair Display","description_typography_font_size":{"unit":"px","size":20,"sizes":[]},"view":"stacked","title_typography_font_weight":"300","icon_size_mobile":{"unit":"px","size":30,"sizes":[]},"description_typography_font_size_mobile":{"unit":"px","size":15,"sizes":[]},"position":"right","content_vertical_alignment":"middle","title_size":"p"},"elements":[],"isInner":false,"widgetType":"icon-box","elType":"widget"}],"isInner":true,"elType":"column"},{"id":"28951c00","settings":{"_column_size":50,"_inline_size":null,"_inline_size_mobile":50},"elements":[{"id":"210ba534","settings":{"selected_icon":{"value":"far fa-clock","library":"fa-regular"},"title_text":"","description_text":"09.00 WITA<br>till 14.00 WITA","primary_color":"#ffd369","icon_space":{"unit":"px","size":20,"sizes":[]},"title_bottom_space":{"unit":"px","size":0,"sizes":[]},"title_color":"#c6c664","title_typography_typography":"custom","title_typography_font_family":"Parisienne","title_typography_font_size":{"unit":"px","size":33,"sizes":[]},"description_color":"#ffffff","description_typography_typography":"custom","description_typography_font_family":"Playfair Display","description_typography_font_size":{"unit":"px","size":20,"sizes":[]},"view":"stacked","title_typography_font_weight":"300","icon_size_mobile":{"unit":"px","size":30,"sizes":[]},"description_typography_font_size_mobile":{"unit":"px","size":15,"sizes":[]},"position":"left","title_size":"p","content_vertical_alignment":"middle"},"elements":[],"isInner":false,"widgetType":"icon-box","elType":"widget"}],"isInner":true,"elType":"column"}],"isInner":true,"elType":"section"}],"isInner":false,"elType":"column"}],"isInner":false,"elType":"section"},{"id":"33a12044","settings":{"background_background":"classic","background_color":"#FFF1CF"},"elements":[{"id":"1d4bc711","settings":{"_column_size":100,"background_background":"classic","background_color":"#ffd369","margin_tablet":{"unit":"px","top":"0","right":"20","bottom":"0","left":"20","isLinked":false},"margin_mobile":{"unit":"px","top":"0","right":"10","bottom":"0","left":"10","isLinked":false},"padding":{"unit":"px","top":"75","right":"0","bottom":"75","left":"0","isLinked":false}},"elements":[{"id":"55674c08","settings":{"image":{"id":"541","url":"https:\/\/tombol.space\/wp-content\/uploads\/2020\/12\/Asset-1.png"},"image_size":"full","align":"center","width":{"unit":"%","size":15,"sizes":[]},"width_tablet":{"unit":"%","size":25,"sizes":[]},"space":{"unit":"%","size":100,"sizes":[]},"space_tablet":{"unit":"%","size":100,"sizes":[]},"_margin":{"unit":"px","top":"-120","right":"0","bottom":"0","left":"0","isLinked":false},"_margin_tablet":{"unit":"px","top":"-115","right":"0","bottom":"0","left":"0","isLinked":false},"fb_value":"0"},"elements":[],"isInner":false,"widgetType":"image","elType":"widget"},{"id":"2bb60404","settings":{"title":"WE'RE GETTING MARRIED\n\n","header_size":"p","align":"center","title_color":"#015668","typography_typography":"custom","typography_font_family":"Playfair Display","typography_font_size":{"unit":"px","size":30,"sizes":[]},"_margin":{"unit":"px","top":"0","right":"0","bottom":"0","left":"0","isLinked":false}},"elements":[],"isInner":false,"widgetType":"heading","elType":"widget"},{"id":"1c38b032","settings":{"title":"Countdown Timer","header_size":"p","align":"center","title_color":"#263f44","typography_typography":"custom","typography_font_family":"Great Vibes","typography_font_size":{"unit":"px","size":50,"sizes":[]},"typography_font_weight":"300","_margin":{"unit":"px","top":"-20","right":"0","bottom":"0","left":"0","isLinked":false},"text_shadow_text_shadow":{"horizontal":0,"vertical":3,"blur":7,"color":"rgba(0,0,0,0.3)"}},"elements":[],"isInner":false,"widgetType":"heading","elType":"widget"},{"id":"6c43f4f9","settings":{"wpkoi_elements_countdown_due_time":"2022-12-12 00:00","wpkoi_elements_countdown_days_label":"Hari","wpkoi_elements_countdown_hours_label":"Jam","wpkoi_elements_countdown_minutes_label":"Menit","wpkoi_elements_countdown_seconds_label":"Detik","wpkoi_elements_countdown_spacing_tablet":{"unit":"px","size":6,"sizes":[]},"wpkoi_elements_countdown_spacing_mobile":{"unit":"px","size":3,"sizes":[]},"wpkoi_elements_countdown_box_padding":{"unit":"px","top":"10","right":"5","bottom":"10","left":"5","isLinked":false},"wpkoi_elements_countdown_box_border_radius":{"unit":"px","top":"15","right":"15","bottom":"15","left":"15","isLinked":true},"wpkoi_elements_countdown_background":"#015668","wpkoi_elements_countdown_digit_typography_typography":"custom","wpkoi_elements_countdown_digit_typography_font_family":"Playfair Display","wpkoi_elements_countdown_digit_typography_font_size_mobile":{"unit":"px","size":35,"sizes":[]},"wpkoi_elements_countdown_digit_typography_line_height":{"unit":"em","size":1.3,"sizes":[]},"wpkoi_elements_countdown_label_typography_typography":"custom","_margin":{"unit":"px","top":"10","right":"250","bottom":"20","left":"250","isLinked":false},"_margin_mobile":{"unit":"px","top":"0","right":"15","bottom":"0","left":"15","isLinked":false},"_background_background":"classic","_margin_tablet":{"unit":"px","top":"0","right":"125","bottom":"0","left":"125","isLinked":false}},"elements":[],"isInner":false,"widgetType":"weddingpress-countdown","elType":"widget"},{"id":"3921ff","settings":{"wp_gallery":[{"id":"401","url":"https:\/\/tombol.space\/wp-content\/uploads\/2020\/12\/pexels-photo-2253867.png"},{"id":"400","url":"https:\/\/tombol.space\/wp-content\/uploads\/2020\/12\/pexels-photo-931796.png"},{"id":"402","url":"https:\/\/tombol.space\/wp-content\/uploads\/2020\/12\/pexels-photo-265730.png"},{"id":"394","url":"https:\/\/tombol.space\/wp-content\/uploads\/2020\/12\/pexels-photo-247858.png"}],"thumbnail_size":"full","gallery_columns":"2","image_border_width":{"unit":"px","top":"5","right":"5","bottom":"5","left":"5","isLinked":true},"image_border_color":"#015668","image_border_radius":{"unit":"px","top":"20","right":"20","bottom":"20","left":"20","isLinked":true},"_margin":{"unit":"px","top":"0","right":"100","bottom":"0","left":"100","isLinked":false},"_margin_mobile":{"unit":"px","top":"0","right":"0","bottom":"0","left":"0","isLinked":false},"_padding":{"unit":"px","top":"20","right":"20","bottom":"20","left":"20","isLinked":true},"_padding_mobile":{"unit":"px","top":"0","right":"20","bottom":"0","left":"20","isLinked":false},"_animation":"rollIn"},"elements":[],"isInner":false,"widgetType":"image-gallery","elType":"widget"}],"isInner":false,"elType":"column"}],"isInner":false,"elType":"section"},{"id":"77aea29b","settings":{"padding_mobile":{"unit":"px","top":"0","right":"0","bottom":"0","left":"0","isLinked":false},"structure":"20","background_background":"classic","background_color":"#FFF1CF"},"elements":[{"id":"4f596d4c","settings":{"_column_size":100,"background_background":"classic","background_color":"#015668","background_overlay_background":"classic","background_overlay_image":{"id":"531","url":"https:\/\/tombol.space\/wp-content\/uploads\/2020\/12\/1.jpg"},"background_overlay_repeat":"repeat","background_overlay_size":"cover","background_overlay_opacity":{"unit":"px","size":0.09,"sizes":[]},"padding":{"unit":"px","top":"100","right":"0","bottom":"100","left":"0","isLinked":false},"margin_tablet":{"unit":"px","top":"0","right":"20","bottom":"0","left":"20","isLinked":false},"margin_mobile":{"unit":"px","top":"0","right":"10","bottom":"0","left":"10","isLinked":false}},"elements":[{"id":"7b76be55","settings":{"address":"desainpromosi","height":{"unit":"px","size":345,"sizes":[]},"_margin":{"unit":"px","top":"-135","right":"200","bottom":"35","left":"200","isLinked":false},"_margin_tablet":{"unit":"px","top":"-150","right":"50","bottom":"0","left":"50","isLinked":false},"_margin_mobile":{"unit":"px","top":"-181","right":"10","bottom":"0","left":"10","isLinked":false},"_padding_tablet":{"unit":"px","top":"0","right":"0","bottom":"0","left":"0","isLinked":false},"_padding_mobile":{"unit":"px","top":"0","right":"0","bottom":"0","left":"0","isLinked":true},"_border_border":"solid","_border_width":{"unit":"px","top":"10","right":"10","bottom":"10","left":"10","isLinked":true},"_border_color":"#263f44","_box_shadow_box_shadow_type":"yes","_box_shadow_box_shadow":{"horizontal":0,"vertical":30,"blur":17,"spread":-19,"color":"rgba(0,0,0,0.21)"},"_z_index":1,"_animation":"fadeInUp"},"elements":[],"isInner":false,"widgetType":"google_maps","elType":"widget"},{"id":"2f3a4741","settings":{"title":"KIRIMKAN PESAN","header_size":"p","align":"center","title_color":"#ffd369","typography_typography":"custom","typography_font_family":"Playfair Display","typography_font_size":{"unit":"px","size":30,"sizes":[]},"_margin":{"unit":"px","top":"0","right":"0","bottom":"0","left":"0","isLinked":false}},"elements":[],"isInner":false,"widgetType":"heading","elType":"widget"},{"id":"321968ef","settings":{"title":"Untuk Kedua Mempelai","header_size":"p","align":"center","title_color":"#ffffff","typography_typography":"custom","typography_font_family":"Great Vibes","typography_font_size":{"unit":"px","size":50,"sizes":[]},"typography_font_weight":"300","_margin":{"unit":"px","top":"-20","right":"0","bottom":"0","left":"0","isLinked":false},"text_shadow_text_shadow":{"horizontal":0,"vertical":3,"blur":7,"color":"rgba(0,0,0,0.3)"}},"elements":[],"isInner":false,"widgetType":"heading","elType":"widget"},{"id":"3bee8ed8","settings":{"data_id":"guestbox","form_labels":"","avatar":{"id":"403","url":"https:\/\/tombol.space\/wp-content\/uploads\/2020\/12\/07.png"},"field_name_label":"Nama","field_name_placeholder":"Isikan Nama","field_message_label":"Pesan","field_message_placeholder":"Tuliskan Pesan dan Doa","field_submit_text":"Kirim Ucapan","typography_typography":"custom","typography_font_family":"ABeeZee","typography_font_size":{"unit":"px","size":18,"sizes":[]},"background_color":"#FFD369","_margin":{"unit":"px","top":"10","right":"150","bottom":"20","left":"150","isLinked":false},"_margin_tablet":{"unit":"px","top":"0","right":"100","bottom":"0","left":"100","isLinked":false},"_margin_mobile":{"unit":"px","top":"0","right":"10","bottom":"0","left":"10","isLinked":false},"button_text_color":"#263F44","border_border":"solid","border_color":"#263F44","border_radius":{"unit":"px","top":"11","right":"11","bottom":"11","left":"11","isLinked":true},"hover_color":"#FFFFFF","button_background_hover_color":"#263F44"},"elements":[],"isInner":false,"widgetType":"weddingpress-guestbook","elType":"widget"}],"isInner":false,"elType":"column"}],"isInner":false,"elType":"section"},{"id":"603ca52a","settings":{"background_background":"classic","shape_divider_bottom_negative":"yes","margin_mobile":{"unit":"px","top":"0","right":0,"bottom":"0","left":0,"isLinked":false},"padding":{"unit":"px","top":"0","right":"0","bottom":"0","left":"0","isLinked":false},"padding_mobile":{"unit":"px","top":"0","right":"0","bottom":"0","left":"0","isLinked":false},"background_color":"#FFF1CF"},"elements":[{"id":"189e8ab9","settings":{"_column_size":100,"background_background":"classic","background_color":"rgba(255,211,105,0.75)","background_overlay_background":"classic","background_overlay_image":{"id":"397","url":"https:\/\/tombol.space\/wp-content\/uploads\/2020\/12\/pexels-photo-256737.png"},"background_overlay_position":"center center","background_overlay_position_tablet":"initial","background_overlay_xpos":{"unit":"px","size":-96,"sizes":[]},"background_overlay_ypos":{"unit":"px","size":71,"sizes":[]},"background_overlay_attachment":"fixed","background_overlay_repeat":"no-repeat","background_overlay_size":"cover","background_overlay_bg_width":{"unit":"%","size":97,"sizes":[]},"background_overlay_opacity":{"unit":"px","size":0.11,"sizes":[]},"border_radius":{"unit":"px","top":"0","right":"0","bottom":"0","left":"0","isLinked":false},"margin_tablet":{"unit":"px","top":"0","right":"20","bottom":"0","left":"20","isLinked":false},"margin_mobile":{"unit":"px","top":"0","right":"10","bottom":"0","left":"10","isLinked":false},"padding":{"unit":"px","top":"100","right":"0","bottom":"100","left":"0","isLinked":false},"padding_mobile":{"unit":"px","top":"50","right":"0","bottom":"50","left":"0","isLinked":false}},"elements":[{"id":"47c757b1","settings":{"title":"\u201cSemoga Allah menghimpun yang terserak dari keduanya, memberkati mereka berdua dan kiranya Allah meningkatkan kualitas keturunan mereka, menjadikannya pembuka pintu rahmat, sumber ilmu dan hikmah serta pemberi rasa aman bagi umat.\u201d<br><br><b>(Doa Nabi Muhammad SAW, pada pernikahan putrinya<br>Fatimah Azzahra dengan Ali Bin Abi Thalib)<\/b>","header_size":"p","align":"center","title_color":"#263f44","typography_typography":"custom","typography_font_family":"Source Serif Pro","typography_font_size":{"unit":"px","size":20,"sizes":[]},"_padding":{"unit":"px","top":"0","right":"100","bottom":"0","left":"100","isLinked":false},"_padding_mobile":{"unit":"px","top":"35","right":"20","bottom":"0","left":"20","isLinked":false},"_margin":{"unit":"px","top":"0","right":"0","bottom":"0","left":"0","isLinked":false},"typography_letter_spacing":{"unit":"px","size":1.1,"sizes":[]},"_padding_tablet":{"unit":"px","top":"0","right":"35","bottom":"0","left":"35","isLinked":false}},"elements":[],"isInner":false,"widgetType":"heading","elType":"widget"}],"isInner":false,"elType":"column"}],"isInner":false,"elType":"section"},{"id":"51ed2c09","settings":{"structure":"33","background_background":"classic","background_color":"#2e2f3a","padding":{"unit":"px","top":"20","right":"0","bottom":"30","left":"0","isLinked":false},"margin_mobile":{"unit":"px","top":"0","right":0,"bottom":"0","left":0,"isLinked":false},"padding_mobile":{"unit":"px","top":"0","right":"0","bottom":"0","left":"0","isLinked":false}},"elements":[{"id":"13207752","settings":{"_column_size":25,"_inline_size":null},"elements":[],"isInner":false,"elType":"column"},{"id":"37ae9ea4","settings":{"_column_size":50,"_inline_size":null},"elements":[{"id":"1ffee870","settings":{"title":"<strong>Elementor for Wedding v01<\/strong>; Template Created by <span style=\"color: #ffffff;\"><a style=\"color: #ffffff;\" href=\"https:\/\/weddingpress.net\/\" target=\"_blank\" rel=\"noopener\">WeddingPress.net<\/a><\/span>","header_size":"p","align":"center","title_color":"#c6c6c6","typography_typography":"custom","typography_font_family":"Playfair Display","typography_font_size":{"unit":"px","size":14,"sizes":[]},"typography_font_weight":"400","typography_line_height":{"unit":"em","size":1.2,"sizes":[]},"_margin":{"unit":"px","top":"0","right":"0","bottom":"0","left":"0","isLinked":false},"_padding_mobile":{"unit":"px","top":"0","right":"10","bottom":"0","left":"10","isLinked":false}},"elements":[],"isInner":false,"widgetType":"heading","elType":"widget"}],"isInner":false,"elType":"column"},{"id":"e5ef4cb","settings":{"_column_size":25,"_inline_size":null},"elements":[],"isInner":false,"elType":"column"}],"isInner":false,"elType":"section"}]}